mzk_aleph/__init__.py
mzk_aleph/__main__.py
mzk_aleph/datatypes.py
mzk_aleph/exceptions.py
mzk_aleph/mzk_client.py
mzk_aleph/nkp_client.py
mzk_aleph/nkp_z3950_session.py
mzk_aleph/tests.py
mzk_aleph/oai/__init__.py
mzk_aleph/oai/session.py
mzk_aleph/schemas/__init__.py
mzk_aleph/schemas/frequency.py
mzk_aleph/schemas/mzk_issue.py
mzk_aleph/schemas/mzk_record.py
mzk_aleph/schemas/parsers.py
mzk_aleph/x/__init__.py
mzk_aleph/x/session.py
mzk_aleph/z3950/__init__.py
mzk_aleph/z3950/session.py
mzk_aleph/z3950/yaz_connectors.py
mzk_aleph/z3950/yaz_types.py
mzk_aleph-1.0.0.dist-info/METADATA
mzk_aleph-1.0.0.dist-info/WHEEL
mzk_aleph-1.0.0.dist-info/top_level.txt
mzk_aleph-1.0.0.dist-info/RECORD
